[
{
"publishingOffice": "青森地方気象台",
"reportDatetime": "2024-04-27T17:00:00+09:00",
"timeSeries": [
{
"areas": [
{
"area": {
"code": "020010",
"name": "津軽"
},
"waves": [
"１メートル",
"１メートル",
"１メートル"
],
"weatherCodes": [
"100",
"201",
"101"
],
"weathers": [
"晴れ",
"くもり　昼過ぎ　まで　時々　晴れ　所により　昼前　まで　霧",
"晴れ　時々　くもり"
],
"winds": [
"北西の風　後　南の風　海上　では　南西の風　やや強く",
"西の風　海上　では　西の風　やや強く",
"北の風　後　東の風"
]
},
{
"area": {
"code": "020020",
"name": "下北"
},
"waves": [
"１．５メートル",
"１メートル",
"１メートル"
],
"weatherCodes": [
"100",
"201",
"101"
],
"weathers": [
"晴れ",
"くもり　昼前　まで　時々　晴れ　所により　昼前　まで　霧",
"晴れ　時々　くもり"
],
"winds": [
"北の風　後　南西の風　海上　では　南西の風　やや強く",
"西の風　海上　では　南西の風　やや強く",
"南の風　後　東の風"
]
},
{
"area": {
"code": "020030",
"name": "三八上北"
},
"waves": [
"１．５メートル",
"１メートル",
"１メートル"
],
"weatherCodes": [
"100",
"111",
"101"
],
"weathers": [
"晴れ",
"晴れ　夕方　から　くもり　所により　昼前　まで　霧",
"晴れ　時々　くもり"
],
"winds": [
"北東の風　後　南の風　海上　では　はじめ　北西の風　やや強く",
"南西の風　後　北の風",
"東の風"
]
}
],
"timeDefines": [
"2024-04-27T17:00:00+09:00",
"2024-04-28T00:00:00+09:00",
"2024-04-29T00:00:00+09:00"
]
},
{
"areas": [
{
"area": {
"code": "020010",
"name": "津軽"
},
"pops": [
"0",
"10",
"10",
"0",
"0"
]
},
{
"area": {
"code": "020020",
"name": "下北"
},
"pops": [
"0",
"10",
"10",
"0",
"0"
]
},
{
"area": {
"code": "020030",
"name": "三八上北"
},
"pops": [
"0",
"0",
"0",
"0",
"0"
]
}
],
"timeDefines": [
"2024-04-27T18:00:00+09:00",
"2024-04-28T00:00:00+09:00",
"2024-04-28T06:00:00+09:00",
"2024-04-28T12:00:00+09:00",
"2024-04-28T18:00:00+09:00"
]
},
{
"areas": [
{
"area": {
"code": "31312",
"name": "青森"
},
"temps": [
"9",
"20"
]
},
{
"area": {
"code": "31602",
"name": "八戸"
},
"temps": [
"10",
"21"
]
},
{
"area": {
"code": "31111",
"name": "むつ"
},
"temps": [
"8",
"21"
]
},
{
"area": {
"code": "31436",
"name": "深浦"
},
"temps": [
"9",
"16"
]
},
{
"area": {
"code": "31461",
"name": "弘前"
},
"temps": [
"8",
"22"
]
}
],
"timeDefines": [
"2024-04-28T00:00:00+09:00",
"2024-04-28T09:00:00+09:00"
]
}
]
},
{
"precipAverage": {
"areas": [
{
"area": {
"code": "31312",
"name": "青森"
},
"max": "20.8",
"min": "7.0"
},
{
"area": {
"code": "31602",
"name": "八戸"
},
"max": "18.5",
"min": "4.5"
}
]
},
"publishingOffice": "青森地方気象台",
"reportDatetime": "2024-04-27T17:00:00+09:00",
"tempAverage": {
"areas": [
{
"area": {
"code": "31312",
"name": "青森"
},
"max": "17.0",
"min": "7.0"
},
{
"area": {
"code": "31602",
"name": "八戸"
},
"max": "17.1",
"min": "7.0"
}
]
},
"timeSeries": [
{
"areas": [
{
"area": {
"code": "020010",
"name": "津軽"
},
"pops": [
"",
"20",
"70",
"50",
"20",
"20",
"20"
],
"reliabilities": [
"",
"",
"A",
"C",
"A",
"A",
"A"
],
"weatherCodes": [
"201",
"101",
"203",
"202",
"101",
"101",
"101"
]
},
{
"area": {
"code": "020200",
"name": "下北・三八上北"
},
"pops": [
"",
"20",
"70",
"50",
"20",
"20",
"20"
],
"reliabilities": [
"",
"",
"B",
"C",
"A",
"A",
"A"
],
"weatherCodes": [
"111",
"101",
"203",
"202",
"101",
"101",
"101"
]
}
],
"timeDefines": [
"2024-04-28T00:00:00+09:00",
"2024-04-29T00:00:00+09:00",
"2024-04-30T00:00:00+09:00",
"2024-05-01T00:00:00+09:00",
"2024-05-02T00:00:00+09:00",
"2024-05-03T00:00:00+09:00",
"2024-05-04T00:00:00+09:00"
]
},
{
"areas": [
{
"area": {
"code": "31312",
"name": "青森"
},
"tempsMax": [
"",
"18",
"17",
"16",
"19",
"22",
"21"
],
"tempsMaxLower": [
"",
"17",
"15",
"14",
"17",
"20",
"17"
],
"tempsMaxUpper": [
"",
"20",
"22",
"18",
"21",
"24",
"25"
],
"tempsMin": [
"",
"8",
"8",
"8",
"7",
"7",
"9"
],
"tempsMinLower": [
"",
"6",
"7",
"6",
"4",
"3",
"5"
],
"tempsMinUpper": [
"",
"10",
"10",
"10",
"9",
"11",
"10"
]
},
{
"area": {
"code": "31602",
"name": "八戸"
},
"tempsMax": [
"",
"18",
"19",
"17",
"20",
"24",
"22"
],
"tempsMaxLower": [
"",
"17",
"16",
"14",
"16",
"21",
"18"
],
"tempsMaxUpper": [
"",
"20",
"23",
"19",
"24",
"27",
"26"
],
"tempsMin": [
"",
"9",
"9",
"9",
"7",
"8",
"10"
],
"tempsMinLower": [
"",
"7",
"7",
"7",
"4",
"4",
"5"
],
"tempsMinUpper": [
"",
"11",
"11",
"11",
"9",
"12",
"11"
]
}
],
"timeDefines": [
"2024-04-28T00:00:00+09:00",
"2024-04-29T00:00:00+09:00",
"2024-04-30T00:00:00+09:00",
"2024-05-01T00:00:00+09:00",
"2024-05-02T00:00:00+09:00",
"2024-05-03T00:00:00+09:00",
"2024-05-04T00:00:00+09:00"
]
}
]
}
]