[
{
"publishingOffice": "秋田地方気象台",
"reportDatetime": "2024-05-15T17:00:00+09:00",
"timeSeries": [
{
"areas": [
{
"area": {
"code": "050010",
"name": "沿岸"
},
"waves": [
"０．５メートル",
"０．５メートル　後　２メートル",
"３メートル　後　５メートル"
],
"weatherCodes": [
"111",
"212",
"203"
],
"weathers": [
"晴れ　夜　くもり",
"くもり　時々　晴れ　夜　雨",
"くもり　時々　雨"
],
"winds": [
"西の風　後　東の風",
"東の風　後　南西の風　やや強く",
"南西の風　強く"
]
},
{
"area": {
"code": "050020",
"name": "内陸"
},
"weatherCodes": [
"111",
"212",
"203"
],
"weathers": [
"晴れ　夜　くもり",
"くもり　時々　晴れ　夜　雨",
"くもり　時々　雨"
],
"winds": [
"北西の風　後　東の風",
"東の風　後　西の風　やや強く",
"西の風　やや強く"
]
}
],
"timeDefines": [
"2024-05-15T17:00:00+09:00",
"2024-05-16T00:00:00+09:00",
"2024-05-17T00:00:00+09:00"
]
},
{
"areas": [
{
"area": {
"code": "050010",
"name": "沿岸"
},
"pops": [
"0",
"0",
"0",
"20",
"80"
]
},
{
"area": {
"code": "050020",
"name": "内陸"
},
"pops": [
"0",
"0",
"0",
"20",
"70"
]
}
],
"timeDefines": [
"2024-05-15T18:00:00+09:00",
"2024-05-16T00:00:00+09:00",
"2024-05-16T06:00:00+09:00",
"2024-05-16T12:00:00+09:00",
"2024-05-16T18:00:00+09:00"
]
},
{
"areas": [
{
"area": {
"code": "32402",
"name": "秋田"
},
"temps": [
"15",
"25"
]
},
{
"area": {
"code": "32126",
"name": "鷹巣"
},
"temps": [
"11",
"27"
]
},
{
"area": {
"code": "32596",
"name": "横手"
},
"temps": [
"13",
"27"
]
}
],
"timeDefines": [
"2024-05-16T00:00:00+09:00",
"2024-05-16T09:00:00+09:00"
]
}
]
},
{
"precipAverage": {
"areas": [
{
"area": {
"code": "32402",
"name": "秋田"
},
"max": "31.0",
"min": "12.7"
}
]
},
"publishingOffice": "秋田地方気象台",
"reportDatetime": "2024-05-15T17:00:00+09:00",
"tempAverage": {
"areas": [
{
"area": {
"code": "32402",
"name": "秋田"
},
"max": "19.9",
"min": "11.6"
}
]
},
"timeSeries": [
{
"areas": [
{
"area": {
"code": "050000",
"name": "秋田県"
},
"pops": [
"",
"80",
"10",
"20",
"30",
"40",
"40"
],
"reliabilities": [
"",
"",
"A",
"A",
"A",
"B",
"B"
],
"weatherCodes": [
"212",
"203",
"101",
"101",
"201",
"200",
"200"
]
}
],
"timeDefines": [
"2024-05-16T00:00:00+09:00",
"2024-05-17T00:00:00+09:00",
"2024-05-18T00:00:00+09:00",
"2024-05-19T00:00:00+09:00",
"2024-05-20T00:00:00+09:00",
"2024-05-21T00:00:00+09:00",
"2024-05-22T00:00:00+09:00"
]
},
{
"areas": [
{
"area": {
"code": "32402",
"name": "秋田"
},
"tempsMax": [
"",
"17",
"24",
"24",
"24",
"22",
"22"
],
"tempsMaxLower": [
"",
"15",
"22",
"22",
"21",
"19",
"19"
],
"tempsMaxUpper": [
"",
"19",
"25",
"27",
"28",
"26",
"27"
],
"tempsMin": [
"",
"11",
"12",
"12",
"12",
"13",
"12"
],
"tempsMinLower": [
"",
"10",
"10",
"11",
"10",
"10",
"9"
],
"tempsMinUpper": [
"",
"13",
"13",
"14",
"15",
"15",
"15"
]
}
],
"timeDefines": [
"2024-05-16T00:00:00+09:00",
"2024-05-17T00:00:00+09:00",
"2024-05-18T00:00:00+09:00",
"2024-05-19T00:00:00+09:00",
"2024-05-20T00:00:00+09:00",
"2024-05-21T00:00:00+09:00",
"2024-05-22T00:00:00+09:00"
]
}
]
}
]